StoryBot/IRC.py
StoryBot/__init__.py
storybot-1.4.1.dist-info/METADATA
storybot-1.4.1.dist-info/RECORD
storybot-1.4.1.dist-info/WHEEL
storybot-1.4.1.dist-info/top_level.txt
