Metadata-Version: 2.1
Name: storybot
Version: 1.4.1
Summary: IRC bot library.
Home-page: UNKNOWN
Author: SkyGen
Author-email: skygen@alwaysdata.net
License: UNKNOWN
Platform: UNKNOWN
Classifier: Programming Language :: Python :: 3
Classifier: Operating System :: OS Independent
